robin_stocks/__init__.py
robin_stocks/account.py
robin_stocks/authentication.py
robin_stocks/constants.py
robin_stocks/crypto.py
robin_stocks/export.py
robin_stocks/globals.py
robin_stocks/helper.py
robin_stocks/markets.py
robin_stocks/options.py
robin_stocks/orders.py
robin_stocks/profiles.py
robin_stocks/robin_stocks.py
robin_stocks/stocks.py
robin_stocks/urls.py
robin_stocks/gemini/__init__.py
robin_stocks/gemini/account.py
robin_stocks/gemini/authentication.py
robin_stocks/gemini/crypto.py
robin_stocks/gemini/globals.py
robin_stocks/gemini/helper.py
robin_stocks/gemini/orders.py
robin_stocks/gemini/urls.py
robin_stocks/robinhood/__init__.py
robin_stocks/robinhood/account.py
robin_stocks/robinhood/authentication.py
robin_stocks/robinhood/crypto.py
robin_stocks/robinhood/export.py
robin_stocks/robinhood/globals.py
robin_stocks/robinhood/helper.py
robin_stocks/robinhood/markets.py
robin_stocks/robinhood/options.py
robin_stocks/robinhood/orders.py
robin_stocks/robinhood/profiles.py
robin_stocks/robinhood/stocks.py
robin_stocks/robinhood/urls.py
robin_stocks/tda/__init__.py
robin_stocks/tda/accounts.py
robin_stocks/tda/authentication.py
robin_stocks/tda/globals.py
robin_stocks/tda/helper.py
robin_stocks/tda/markets.py
robin_stocks/tda/orders.py
robin_stocks/tda/stocks.py
robin_stocks/tda/urls.py
tests/__init__.py
tests/app_tests.py
tests/test_app.py
tests/test_automated.py
tests/test_gemini.py
tests/test_github_actions.py
tests/test_robinhood.py
tests/test_tda.py
robin_stocks-3.4.0.dist-info/LICENSE.txt
robin_stocks-3.4.0.dist-info/METADATA
robin_stocks-3.4.0.dist-info/WHEEL
robin_stocks-3.4.0.dist-info/top_level.txt
robin_stocks-3.4.0.dist-info/RECORD
