Metadata-Version: 2.1
Name: robin-stocks
Version: 3.4.0
Summary: A Python wrapper around the Robinhood API
Home-page: https://github.com/jmfernandes/robin_stocks
Author: Josh Fernandes
Author-email: joshfernandes@mac.com
License: MIT
Keywords: robinhood,robin stocks,finance app,stocks,options,trading,investing
Requires: requests
Requires: pyotp
Requires: cryptography
Requires-Python: >=3.9
License-File: LICENSE.txt
